<annotation><folder>Images</folder><filename>screenshot_63.png</filename><source><database>Unknown</database></source><size><width>800</width><height>380</height><depth>3</depth></size><segmented>0</segmented><object><name>gold</name><pose>Unspecified</pose><truncated>0</truncated><difficult>0</difficult><bndbox><xmin>510</xmin><ymin>171</ymin><xmax>522</xmax><ymax>200</ymax></bndbox></object><object><name>gold</name><pose>Unspecified</pose><truncated>0</truncated><difficult>0</difficult><bndbox><xmin>538</xmin><ymin>139</ymin><xmax>556</xmax><ymax>164</ymax></bndbox></object><object><name>gold</name><pose>Unspecified</pose><truncated>0</truncated><difficult>0</difficult><bndbox><xmin>539</xmin><ymin>171</ymin><xmax>558</xmax><ymax>198</ymax></bndbox></object><object><name>gold</name><pose>Unspecified</pose><truncated>0</truncated><difficult>0</difficult><bndbox><xmin>664</xmin><ymin>265</ymin><xmax>685</xmax><ymax>293</ymax></bndbox></object><object><name>gold</name><pose>Unspecified</pose><truncated>0</truncated><difficult>0</difficult><bndbox><xmin>638</xmin><ymin>264</ymin><xmax>649</xmax><ymax>293</ymax></bndbox></object><object><name>gold</name><pose>Unspecified</pose><truncated>0</truncated><difficult>0</difficult><bndbox><xmin>638</xmin><ymin>299</ymin><xmax>650</xmax><ymax>324</ymax></bndbox></object></annotation>