<annotation><folder>Images</folder><filename>screenshot_53.png</filename><source><database>Unknown</database></source><size><width>800</width><height>380</height><depth>3</depth></size><segmented>0</segmented><object><name>trap_off</name><pose>Unspecified</pose><truncated>0</truncated><difficult>0</difficult><bndbox><xmin>426</xmin><ymin>310</ymin><xmax>489</xmax><ymax>370</ymax></bndbox></object><object><name>door</name><pose>Unspecified</pose><truncated>0</truncated><difficult>0</difficult><bndbox><xmin>745</xmin><ymin>84</ymin><xmax>800</xmax><ymax>150</ymax></bndbox></object></annotation>